{"add":{"path":"part-00001-fda45d85-5d62-4038-81ce-28ede98962c0-c000.snappy.parquet","partitionValues":{},"size":433342,"modificationTime":1732585268571,"dataChange":true,"stats":"{\"numRecords\":12428,\"minValues\":{\"symbol\":\"020Y.L\",\"exchange\":\"American Stock Exchange\",\"price\":-0.0,\"exchangeShortName\":\"AMEX\",\"name\":\"-1x Short VIX Futures ETF\",\"type\":\"etf\"},\"maxValues\":{\"symbol\":\"ZZZD.TO\",\"price\":129600.0,\"name\":\"wShares Enhanced Gold ETF\",\"type\":\"etf\",\"exchange\":\"XETRA\",\"exchangeShortName\":\"XETRA\"},\"nullCount\":{\"exchange\":1,\"symbol\":0,\"name\":2,\"exchangeShortName\":1,\"price\":24,\"type\":0}}","tags":null,"deletionVector":null,"baseRowId":null,"defaultRowCommitVersion":null,"clusteringProvider":null}}
{"remove":{"path":"part-00001-6553d264-5be0-4a53-b33f-99a5482d1561-c000.snappy.parquet","dataChange":true,"deletionTimestamp":1732585268571,"extendedFileMetadata":true,"partitionValues":{},"size":433595}}
{"commitInfo":{"timestamp":1732585268574,"operation":"MERGE","operationParameters":{"notMatchedPredicates":"[{\"actionType\":\"insert\"}]","notMatchedBySourcePredicates":"[]","matchedPredicates":"[{\"actionType\":\"update\"}]","mergePredicate":"target.symbol = source.symbol","predicate":"symbol BETWEEN '020Y.L' AND 'ZZZD.TO'"},"clientVersion":"delta-rs.0.21.0","readVersion":0,"operationMetrics":{"execution_time_ms":431,"num_output_rows":12428,"num_source_rows":12428,"num_target_files_added":1,"num_target_files_removed":1,"num_target_files_scanned":1,"num_target_files_skipped_during_scan":0,"num_target_rows_copied":0,"num_target_rows_deleted":0,"num_target_rows_inserted":0,"num_target_rows_updated":12428,"rewrite_time_ms":123,"scan_time_ms":0}}}